{
	"response": [
		{
			"maintainer": "svasiliev22",
			"oem": "",
			"device": "Poco X5 Pro 5G",
			"filename": "BaikalOS-13-redwood-DEV-20231018-01.zip",
			"download": "https://sourceforge.net/projects/baikalos/files/redwood/BaikalOS-13-redwood-DEV-20231018-01.zip/download",
			"timestamp": 1697607716,
			"md5": "d7ef80c0dd7c07ab702e66189773d625",
			"sha256": "cda79af66724b08ef7b739321dabfd5f4fa7af32fab6415ed97959b5cd06b85b",
			"size": 1428123023,
			"version": "20231018-01.zip",
			"buildtype": "OFFICIAL",
			"forum": "",
			"gapps": "",
			"firmware": "",
			"modem": "",
			"bootloader": "",
			"recovery": "",
			"paypal": "",
			"telegram": "",
			"dt": "",
			"common-dt": "",
			"kernel": ""
		}
	]
}
