{
	"response": [
		{
			"maintainer": "svasiliev22",
			"oem": "",
			"device": "Poco X5 Pro 5G",
			"filename": "BaikalOS-13-redwood-DEV-20241015-03.zip",
			"download": "https://sourceforge.net/projects/baikalos/files/redwood/BaikalOS-13-redwood-DEV-20241015-03.zip/download",
			"timestamp": 1728984216,
			"md5": "9eadc173acb6a540d75df742a587cb6d",
			"sha256": "879c871ec87d427b6e6bc15b77e4205ad99e527175c5b0eda1015eb4089bc5f4",
			"size": 1426079415,
			"version": "20241015-03.zip",
			"buildtype": "OFFICIAL",
			"forum": "",
			"gapps": "",
			"firmware": "",
			"modem": "",
			"bootloader": "",
			"recovery": "",
			"paypal": "",
			"telegram": "",
			"dt": "",
			"common-dt": "",
			"kernel": ""
		}
	]
}
